.DS_Store
General_Deep_Q_RL/MG_data.py
General_Deep_Q_RL/__init__.py
General_Deep_Q_RL/agent.py
General_Deep_Q_RL/agent_ale.py
General_Deep_Q_RL/base_classes.py
General_Deep_Q_RL/core_optim.py
General_Deep_Q_RL/default_parser.py
General_Deep_Q_RL/run_ALE.py
General_Deep_Q_RL/run_MG_two_storages.py
General_Deep_Q_RL/run_toy_env.py
deeprl/MG_data.py
deeprl/__init__.py
deeprl/agent.py
deeprl/agent_ale.py
deeprl/base_classes.py
deeprl/core_optim.py
deeprl/default_parser.py
deeprl/run_ALE.py
deeprl/run_MG_two_storages.py
deeprl/run_toy_env.py
deeprl/experiment/__init__.py
deeprl/experiment/base_controllers.py
deeprl/q_networks/__init__.py
deeprl/q_networks/q_net_lasagne.py
deeprl/q_networks/q_net_theano.py
deeprl/q_networks/theano_layers.py
deeprl/q_networks/updates.py
deeprl/tests/__init__.py
deeprl/tests/test_base.py
deer/MG_data.py
deer/__init__.py
deer/agent-exp_replay.py
deer/agent.py
deer/agent_ale.py
deer/agent_old.py
deer/base_classes.py
deer/default_parser.py
deer/base_classes/QNetwork.py
deer/base_classes/__init__.py
deer/base_classes/environment.py
deer/base_classes/learning_algo.py
deer/base_classes/policy.py
deer/experiment/__init__.py
deer/experiment/base_controllers.py
deer/experiment/base_controllers_BACKUP_3315.py
deer/experiment/base_controllers_BASE_3315.py
deer/experiment/base_controllers_LOCAL_3315.py
deer/experiment/base_controllers_REMOTE_3315.py
deer/helper/__init__.py
deer/helper/plot_abstract_repr.py
deer/helper/plots.py
deer/helper/special_convolutions.py
deer/helper/tree.py
deer/learning_algos/AC_net_keras.py
deer/learning_algos/CRAR_keras.py
deer/learning_algos/CRAR_keras_explo.py
deer/learning_algos/CRAR_keras_withautoenc.py
deer/learning_algos/CRAR_modif_keras.py
deer/learning_algos/CRAR_stoch_keras_WGAN.py
deer/learning_algos/CRAR_stoch_keras_b.py
deer/learning_algos/CRAR_stoch_keras_backup.py
deer/learning_algos/CRAR_stoch_keras_backup2.py
deer-0.4.3.dist-info/METADATA
deer-0.4.3.dist-info/RECORD
deer-0.4.3.dist-info/WHEEL
deer-0.4.3.dist-info/top_level.txt
